factor_backtester/FactorBacktester.py
factor_backtester/__init__.py
factor_backtester-1.0.1.dist-info/LICENSE
factor_backtester-1.0.1.dist-info/METADATA
factor_backtester-1.0.1.dist-info/WHEEL
factor_backtester-1.0.1.dist-info/top_level.txt
factor_backtester-1.0.1.dist-info/RECORD
