Metadata-Version: 2.1
Name: factor_backtester
Version: 1.0.1
Summary: A tool for factor backtesting
Home-page: https://github.com/AlfredCYL/factor_backtester
Author: AlfredCYL
Author-email: alfred.yl@outlook.com
Classifier: Programming Language :: Python :: 3
Classifier: License :: OSI Approved :: MIT License
Classifier: Operating System :: OS Independent
Requires-Python: >=3.6
License-File: LICENSE
Requires-Dist: numpy
Requires-Dist: pandas
Requires-Dist: matplotlib
Requires-Dist: statsmodels
Requires-Dist: tabulate
Requires-Dist: numba
